[{"id": "SDMT-011", "page_url": "https://www.33fanhao.com/vod-read-id-102687.html", "title": "\u7d20\u4eba\u5a18\u304c\u8d64\u9762\u624b\u30b3\u30ad\u3067\u30b6\u30fc\u30e1\u30f3\u767a\u5c04", "issue_time": "2010-02-04", "company": "SOD\u30af\u30ea\u30a8\u30a4\u30c8$$$SOFT ON DEMAND", "duration": "130\u5206\u949f"}, {"id": "SDMT-014", "page_url": "https://www.33fanhao.com/vod-read-id-102686.html", "title": "\u5bc6\u5ba4\u3067\u5973\u5b50\u6821\u751f\u306b\u3055\u308c\u305f\u6027\u7684\u304a\u4ed5\u7f6e\u304d", "issue_time": "2010-02-04", "company": "SOD\u30af\u30ea\u30a8\u30a4\u30c8$$$SOD\u30af\u30ea\u30a8\u30a4\u30c8", "duration": "99\u5206\u949f"}, {"id": "MOMJ-083", "page_url": "https://www.33fanhao.com/vod-read-id-102685.html", "title": "\u3053\u3093\u306a\u79c1\u3067\u3054\u3081\u3093\u306a\u3055\u3044\u2026 \u52a0\u85e4\u30c4\u30d0\u30ad", "issue_time": "2010-02-04", "company": "\u30bf\u30ab\u30e9\u6620\u50cf$$$MOMIJI", "duration": "119\u5206\u949f"}, {"id": "SDMT-010", "page_url": "https://www.33fanhao.com/vod-read-id-102684.html", "title": "\u90e8\u6d3b\u5e30\u308a\u30b3\u30f3\u30d3\u30cb\u3067\u5c6f\u3059\u308b\u7530\u820e\u5973\u5b50\u6821\u751f \u6559\u79d1\u66f8\u306b\u306f\u66f8\u3044\u3066\u306a\u3044\u30aa\u30c8\u30ca\u306e\u4fdd\u5065\u4f53\u80b2\u3092\u5b66\u3093\u3067\u3082\u3089\u3044\u307e\u3057\u305f\u3002", "issue_time": "2010-02-04", "company": "SOD\u30af\u30ea\u30a8\u30a4\u30c8$$$SOD\u30af\u30ea\u30a8\u30a4\u30c8", "duration": "133\u5206\u949f"}, {"id": "SDDE-211", "page_url": "https://www.33fanhao.com/vod-read-id-102683.html", "title": "\u5973\u5b50\u25cf\u7b49\u5b66\u6821 \u5b9a\u671f\u5065\u5eb7\u8a3a\u65ad", "issue_time": "2010-02-04", "company": "SOD\u30af\u30ea\u30a8\u30a4\u30c8$$$SOD\u30af\u30ea\u30a8\u30a4\u30c8", "duration": "129\u5206\u949f"}, {"id": "DVDES-275", "page_url": "https://www.33fanhao.com/vod-read-id-102682.html", "title": "\u6deb\u7325\u30ec\u30ba\u30d0\u30c8\u30eb VOL.2 \u30a8\u30ea\u30fc\u30c8\u5973\u793e\u9577\u59bbvs\u30bb\u30ec\u30d6\u59bb", "issue_time": "2010-02-04", "company": "\u30c7\u30a3\u30fc\u30d7\u30b9$$$DEEP\u2019S", "duration": "158\u5206\u949f"}, {"id": "GAR-151", "page_url": "https://www.33fanhao.com/vod-read-id-102681.html", "title": "\u92ad\u6e6f\u3067\u6d17\u4f53\u3092\u3057\u3066\u304f\u308c\u308b\u5de8\u4e73\u30ae\u30e3\u30eb\u306b\u52c3\u8d77\u30c1\u25cf\u30dd\u304c\u30d0\u30ec\u305f\u3089\u305d\u306e\u67d4\u3089\u304b\u304f\u3066\u6c17\u6301\u3061\u304c\u3044\u3044\u25c6\u304a\u3063\u3071\u3044\u3067\u629c\u304b\u308c\u305f\u3002", "issue_time": "2010-02-04", "company": "GARCON$$$GARCON", "duration": "132\u5206\u949f"}, {"id": "HBAD-116", "page_url": "https://www.33fanhao.com/vod-read-id-102680.html", "title": "\u6e05\u5ec9\u59bb \u592b\u306b\u5185\u7dd2\u306e\u6fe1\u308c\u305f\u8276\u808c \u9ed2\u6728\u9ebb\u8863", "issue_time": "2010-02-04", "company": "\u30d2\u30d3\u30ce$$$HIBINO", "duration": "111\u5206\u949f"}, {"id": "HBAD-115", "page_url": "https://www.33fanhao.com/vod-read-id-102678.html", "title": "\u79d8\u5bc6\u306e\u8089\u4f53\u95a2\u4fc2 \u5144\u3068\u59b9 \u9234\u6728\u30df\u30f3\u30c8", "issue_time": "2010-02-04", "company": "\u30d2\u30d3\u30ce$$$HIBINO", "duration": "120\u5206\u949f"}, {"id": "VSPDS-470", "page_url": "https://www.33fanhao.com/vod-read-id-102679.html", "title": "\u3082\u3057\u3082\u3053\u3093\u306a\u25cb\u25cb\u304cSP \u6708\u91ce\u308a\u3055\u304c\u30da\u30c3\u30c8\u306b\u306a\u3063\u305f\u3089\u2026", "issue_time": "2010-02-04", "company": "V\uff06R\u30d7\u30ed\u30c0\u30af\u30c4$$$V\uff06R\u30d7\u30ed\u30c0\u30af\u30c4", "duration": "99\u5206\u949f"}, {"id": "BKSP-251", "page_url": "https://www.33fanhao.com/vod-read-id-102673.html", "title": "\u900f\u660e\u4eba\u9593\u306b\u306a\u308c\u305f\u50d5\uff01\uff01 2", "issue_time": "2010-02-04", "company": "\u30a2\u30a4\u30a8\u30ca\u30b8\u30fc$$$IE NERGY\uff01", "duration": "113\u5206\u949f"}, {"id": "SDMT-012", "page_url": "https://www.33fanhao.com/vod-read-id-102674.html", "title": "\u7d20\u4eba\u5a18\u304cM\u5b57\u958b\u811a\u3067\u4f55\u5ea6\u3082\u30a4\u30c3\u3061\u3083\u3046\u751f\u30af\u30ea\u30c8\u30ea\u30b9\u3092\u96fb\u30de\u3067\u30d6\u30eb\u30d6\u30eb", "issue_time": "2010-02-04", "company": "SOD\u30af\u30ea\u30a8\u30a4\u30c8$$$SOFT ON DEMAND", "duration": "134\u5206\u949f"}, {"id": "IESP-529", "page_url": "https://www.33fanhao.com/vod-read-id-102675.html", "title": "\u9ebb\u85ac\u635c\u67fb\u5b98 \u30e4\u30af\u6f2c\u3051\u81a3\u75d9\u6523 \u96ea\u898b\u7d17\u5f25", "issue_time": "2010-02-04", "company": "\u30a2\u30a4\u30a8\u30ca\u30b8\u30fc$$$\u66b4\u5922", "duration": "110\u5206\u949f"}, {"id": "DVDES-276", "page_url": "https://www.33fanhao.com/vod-read-id-102676.html", "title": "\u30a2\u30ca\u30eb\u62f7\u554f \uff5e\u30b5\u30fc\u30c9\u30b7\u30fc\u30ba\u30f3\uff5e \u7ffc\u88d5\u9999", "issue_time": "2010-02-04", "company": "\u30c7\u30a3\u30fc\u30d7\u30b9$$$DEEP\u2019S", "duration": "131\u5206\u949f"}, {"id": "FSET-239", "page_url": "https://www.33fanhao.com/vod-read-id-102677.html", "title": "\u5feb\u697d\u6771\u4eac\u30a2\u30af\u30e1\u30b5\u30ed\u30f3", "issue_time": "2010-02-04", "company": "\u30a2\u30ad\u30ce\u30ea$$$AKNR", "duration": "127\u5206\u949f"}, {"id": "RCT-187", "page_url": "https://www.33fanhao.com/vod-read-id-102672.html", "title": "\u96fb\u6d41\u30a2\u30af\u30e1 \uff5e\u52c3\u8d77\u30af\u30ea\u30c8\u30ea\u30b9\u96fb\u6975\u8cac\u3081\uff5e \u7dcf\u96c6\u7de84\u6642\u9593DX", "issue_time": "2010-02-04", "company": "ROCKET$$$ROCKET", "duration": "242\u5206\u949f"}, {"id": "HAVD-656", "page_url": "https://www.33fanhao.com/vod-read-id-102671.html", "title": "\u7d20\u4eba\u5a18\u6fc0\u64ae \u751f\u30d1\u30f3\u30c1\u30e9\u751f\u4e2d\u51fa\u3057\u30ca\u30f3\u30d1 Vol.6", "issue_time": "2010-02-04", "company": "\u30d2\u30d3\u30ce$$$HIBINO", "duration": "111\u5206\u949f"}, {"id": "JPDRS-1663", "page_url": "https://www.33fanhao.com/vod-read-id-102670.html", "title": "\u5b8c\u5168\u5fa9\u523b\u76e4\uff01 \u4eba\u59bb\u30ca\u30f3\u30d1\u5168\u96c6R-13", "issue_time": "2010-02-04", "company": "\u30b7\u30e5\u30ac\u30fc\u30ef\u30fc\u30af\u30b9$$$\u30b8\u30e5\u30fc\u30b7\u30fc", "duration": "240\u5206\u949f"}, {"id": "JPDRS-1662", "page_url": "https://www.33fanhao.com/vod-read-id-102669.html", "title": "\u9650\u5b9a\u5b8c\u5168\u5fa9\u523b\u7248 \u571f\u4e0b\u5ea7\u30ca\u30f3\u30d1\u5168\u96c6 X-18", "issue_time": "2010-02-04", "company": "\u30b7\u30e5\u30ac\u30fc\u30ef\u30fc\u30af\u30b9$$$\u30b8\u30e5\u30fc\u30b7\u30fc", "duration": "238\u5206\u949f"}, {"id": "SDMS-997", "page_url": "https://www.33fanhao.com/vod-read-id-102668.html", "title": "Black Sod \uff5eOFFICIAL COMPLETE EDITION\uff5e", "issue_time": "2010-02-04", "company": "SOD\u30af\u30ea\u30a8\u30a4\u30c8$$$SOD\u30af\u30ea\u30a8\u30a4\u30c8", "duration": "241\u5206\u949f"}, {"id": "STAR-204", "page_url": "https://www.33fanhao.com/vod-read-id-102667.html", "title": "\u82b8\u80fd\u4eba \u3042\u3044\u3060\u3055\u304f\u3089 \u63f4\u25cb\u4e2d\u51fa\u3057", "issue_time": "2010-02-04", "company": "SOD\u30af\u30ea\u30a8\u30a4\u30c8$$$SOD\u30af\u30ea\u30a8\u30a4\u30c8", "duration": "126\u5206\u949f"}, {"id": "IESP-530", "page_url": "https://www.33fanhao.com/vod-read-id-102666.html", "title": "\u56e3\u5730\u59bb\u306e\u6182\u3044 \u8af8\u661f\u30bb\u30a4\u30e9", "issue_time": "2010-02-04", "company": "\u30a2\u30a4\u30a8\u30ca\u30b8\u30fc$$$\u66b4\u5922", "duration": "120\u5206\u949f"}, {"id": "GAR-152", "page_url": "https://www.33fanhao.com/vod-read-id-102665.html", "title": "\u30ae\u30e3\u30eb\u30ec\u30ba\u30ec\u30a4\u30d7\uff01\uff01\u30e0\u30ab\u3064\u304f\u30ae\u30e3\u30eb\u306b\u30da\u30cb\u30d0\u30f3\u9675\u8fb1FUCK\u5236\u88c1\uff01\uff01\uff01", "issue_time": "2010-02-04", "company": "GARCON$$$GARCON", "duration": "124\u5206\u949f"}, {"id": "NHDT-933", "page_url": "https://www.33fanhao.com/vod-read-id-102660.html", "title": "\u30af\u30e9\u30b7\u30c3\u30af\u30b7\u30ea\u30fc\u30ba \u30a2\u30f3\u30c121\u4eba\u75f4\u6f22 VOL.3", "issue_time": "2010-02-04", "company": "\u30ca\u30c1\u30e5\u30e9\u30eb\u30cf\u30a4$$$NATURAL HIGH", "duration": "83\u5206\u949f"}, {"id": "DVDES-278", "page_url": "https://www.33fanhao.com/vod-read-id-102661.html", "title": "\u8131\u304c\u305b\u3066\u307f\u305b\u307e\u3059\uff01\u696d\u754c\u3067\u8a55\u5224\u306e\u8ab0\u3082\u304c1\u79d2\u3067\u604b\u306b\u843d\u3061\u308b\u77e5\u7684\u3067\u30b0\u30e9\u30de\u30e9\u30b9\u306a\u7f8e\u4eba\u30de\u30cd\u30fc\u30b8\u30e3\u30fc 3", "issue_time": "2010-02-04", "company": "\u30c7\u30a3\u30fc\u30d7\u30b9$$$DEEP\u2019S", "duration": "130\u5206\u949f"}, {"id": "VGD-132", "page_url": "https://www.33fanhao.com/vod-read-id-102662.html", "title": "\u30ed\u30ea \u30b9\u30fc\u30d1\u30fc\u30d9\u30b9\u30c8 20\u4eba4\u6642\u9593 \u4e0a\u5dfb", "issue_time": "2010-02-04", "company": "\u30e9\u30b9\u30c8\u30e9\u30b9$$$LUSTROUS", "duration": "242\u5206\u949f"}, {"id": "RCT-186", "page_url": "https://www.33fanhao.com/vod-read-id-102663.html", "title": "\u30b9\u30b1\u30d9\u306a\u89aa\u5b50\u304c\u30a8\u30c3\u30c1\u306a\u30b2\u30fc\u30e0\u4e00\u8ee2\u77e5\u3089\u305a\u306b\u8fd1\u89aa\u76f8\u59e6 \u7236\u89aa\u306a\u3089\u5a18\u306e\u88f8\u5f53\u3066\u3066\u307f\u3066\uff01\u7f8e\u4eba\u59c9\u59b9\u30b9\u30da\u30b7\u30e3\u30eb \uff5e\u898b\u3066\u3001\u89e6\u3063\u3066\u3001\u30cf\u30e1\u3066\u3001\u7236\u89aa\u306f\u30ab\u30e9\u30c0\u306e\u30d1\u30fc\u30c4\u3060\u3051\u3067\u81ea\u5206\u306e\u5a18\u304c\u308f\u304b\u308b\u304b\u306a\uff01\uff1f", "issue_time": "2010-02-04", "company": "ROCKET$$$ROCKET", "duration": "136\u5206\u949f"}, {"id": "NHDT-935", "page_url": "https://www.33fanhao.com/vod-read-id-102664.html", "title": "\u7530\u820e\u306e\u30d8\u30eb\u30e1\u30c3\u30c8\u25cb\u25cb\u751f\u306b\u4e2d\u51fa\u3057 6", "issue_time": "2010-02-04", "company": "\u30ca\u30c1\u30e5\u30e9\u30eb\u30cf\u30a4$$$NATURAL HIGH", "duration": "109\u5206\u949f"}, {"id": "HUNT-268", "page_url": "https://www.33fanhao.com/vod-read-id-102659.html", "title": "\u5bbf\u76f4\u5ba4\u306b\u904a\u3073\u306b\u3084\u3063\u3066\u6765\u308b\u3046\u3076\u306a\u751f\u5f92\u9054\u306f\u3001\u30b3\u30bf\u30c4\u306e\u4e2d\u3067\u5148\u751f\u306b\u3053\u3063\u305d\u308a\u30ef\u30ec\u30e1\u3092\u3044\u3058\u3089\u308c\u3066\u3044\u308b\uff01", "issue_time": "2010-02-04", "company": "Hunter$$$Hunter\uff08\u30bd\u30d5\u30c8\u30aa\u30f3\u30c7\u30de\u30f3\u30c9\uff09", "duration": "127\u5206\u949f"}, {"id": "UURU-026", "page_url": "https://www.33fanhao.com/vod-read-id-102637.html", "title": "\u90e8\u4e0b\u306b\u5bdd\u53d6\u3089\u308c\u305f\u59bb \u677e\u672c\u3042\u3084\u306e", "issue_time": "2010-02-04", "company": "\u30bb\u30f3\u30bf\u30fc\u30d3\u30ec\u30c3\u30b8$$$\u3042\u3058\u3055\u3044", "duration": "88\u5206\u949f"}, {"id": "DKTP-087", "page_url": "https://www.33fanhao.com/vod-read-id-102636.html", "title": "\u30aa\u30a4\u30eb\u30de\u30c3\u30b5\u30fc\u30b8\u3067\u3055\u3093\u3056\u3093\u7126\u3089\u3057\u305f\u6319\u53e5\u3001\u30ba\u30dc\u30f3\u306e\u4e0a\u304b\u3089\u3067\u3082\u5206\u304b\u308b\u304f\u3089\u3044\u30ae\u30f3\u30ae\u30f3\u306e\u30c1\u25cb\u30dd\u3092\u898b\u305b\u3064\u3051\u3001\u305d\u306e\u6c17\u306b\u3055\u305b\u3066\u751f\u633f\u5165\u3057\u3066\u3057\u307e\u3046\u30b9\u30b1\u30d9\u306a\u30de\u30c3\u30b5\u30fc\u30b8\u5e2b\u304c\u3044\u308b\u3089\u3057\u3044\u2026", "issue_time": "2010-02-04", "company": "\u76d7\u64ae\u5929\u56fd$$$\u56db\u8c37\u6620\u50cf", "duration": "118\u5206\u949f"}, {"id": "JPDRS-1661", "page_url": "https://www.33fanhao.com/vod-read-id-102635.html", "title": "\u8ffd\u8de1FUCK\uff01\uff01 \u7d9a\u30fb\u4eba\u59bb\u30ca\u30f3\u30d1217 \uff5e\u7dcf\u6b66\u6cbf\u7dda \u8239\u6a4b\u30fb\u4e80\u6238\u571f\u4e0b\u5ea7\uff5e", "issue_time": "2010-02-04", "company": "\u30b7\u30e5\u30ac\u30fc\u30ef\u30fc\u30af\u30b9$$$\u30b8\u30e5\u30fc\u30b7\u30fc", "duration": "119\u5206\u949f"}, {"id": "VSPDS-471", "page_url": "https://www.33fanhao.com/vod-read-id-102633.html", "title": "\u67d0\u533b\u5927\u75c5\u9662\u306b\u5165\u9662\u3059\u308c\u3070\u5de8\u4e73\u30ca\u30fc\u30b9\u3068\u78ba\u5b9f\u306b\u30e4\u30ec\u308b\uff01", "issue_time": "2010-02-04", "company": "V\uff06R\u30d7\u30ed\u30c0\u30af\u30c4$$$V\uff06R\u30d7\u30ed\u30c0\u30af\u30c4", "duration": "96\u5206\u949f"}, {"id": "GAR-150", "page_url": "https://www.33fanhao.com/vod-read-id-102634.html", "title": "\u9ed2\u30ae\u30e3\u30eb\u3060\u3088\uff01\uff01\u5168\u54e1\u96c6\u5408\uff01\uff01\uff01\u30a4\u30bf\u30ba\u30e9\u9006\u30ca\u30f3\u306f\u30de\u30b8\u3084\u3070\u304f\u306d\u3047\uff5e\uff01\uff01\uff01 VOL.02", "issue_time": "2010-02-04", "company": "GARCON$$$GARCON", "duration": "124\u5206\u949f"}, {"id": "IMGS-043", "page_url": "https://www.33fanhao.com/vod-read-id-102632.html", "title": "\u5352\u696d \u5de3\u7acb\u3061\u306e\u3068\u304d", "issue_time": "2010-02-04", "company": "NEXT GROUP$$$\u30a4\u30de\u30fc\u30b8\u30e5", "duration": "88\u5206\u949f"}, {"id": "BKSP-250", "page_url": "https://www.33fanhao.com/vod-read-id-102631.html", "title": "\u8857\u89d2\u7d20\u4eba\u30ab\u30c3\u30d7\u30eb\u5bfe\u6297\uff01\uff01\u5f7c\u6c0f\u306e\u30c1\u25cb\u30dd\u65e9\u5f53\u3066\u9078\u624b\u6a29\uff01\uff01 3", "issue_time": "2010-02-04", "company": "\u30a2\u30a4\u30a8\u30ca\u30b8\u30fc$$$BKSP", "duration": "123\u5206\u949f"}, {"id": "HAVD-653", "page_url": "https://www.33fanhao.com/vod-read-id-102630.html", "title": "\u8857\u89d2\u7d20\u4eba\u5a18 \u65b0\u30cf\u30e1\u3061\u3083\u3046\u306e\u306f\u8ab0\u3060\uff01\uff01 VOL.19", "issue_time": "2010-02-04", "company": "\u30d2\u30d3\u30ce$$$HIBINO", "duration": "121\u5206\u949f"}, {"id": "NHDT-930", "page_url": "https://www.33fanhao.com/vod-read-id-102629.html", "title": "\u6975\u4e0a\u7d20\u4eba\u304a\u3082\u3044\u3063\u304d\u308a\u751f\u96fb\u30de 3", "issue_time": "2010-02-04", "company": "\u30ca\u30c1\u30e5\u30e9\u30eb\u30cf\u30a4$$$NATURAL HIGH", "duration": "233\u5206\u949f"}, {"id": "FTA-120", "page_url": "https://www.33fanhao.com/vod-read-id-102647.html", "title": "\u3044\u3044\u306a\u308a\u3002\u5bb6\u51fa\u63b2\u793a\u677f\u66f8\u304d\u8fbc\u307f\u5c11\u5973\u2026\u4eee\u540d\u3055\u3084", "issue_time": "2010-02-03", "company": "\u30b0\u30ec\u30a4\u30ba$$$\u30c1\u30fc\u30e0\u5ddd\u5d0e", "duration": "118\u5206\u949f"}, {"id": "NRYO-021", "page_url": "https://www.33fanhao.com/vod-read-id-102638.html", "title": "\u5922\u58f2\u308a\u5c4b \u8d85\u4e0a\u54c1\u30bb\u30ec\u30d6\u5965\u69d8\u6b8b\u9177\u5351\u7325\u5c48\u8fb1\u8089\u68d2\u5730\u7344", "issue_time": "2010-02-03", "company": "\u5973\u4f53\u63a2\u7a76\u51cc\u8fb1\u7814\u7a76\u6240$$$\u5973\u4f53\u63a2\u6c42\u51cc\u8fb1\u7814\u7a76\u6240", "duration": "84\u5206\u949f"}]