[{"id": "TEZ-134", "page_url": "https://www.33fanhao.com/vod-read-id-147966.html", "title": "JK\u30a2\u30bf\u30c3\u30af\u80f8\u30c1\u30e9DX \u7dcf\u96c6\u7de8", "issue_time": "2011-12-28", "company": "\u4fe1\u5dde\u66f8\u5e97$$$\u3064\u3061\u306e\u3053\u6620\u50cf", "duration": "122\u5206\u949f"}, {"id": "TEZ-142", "page_url": "https://www.33fanhao.com/vod-read-id-147964.html", "title": "\u30d1\u30f3\u30c1\u30e9\u3064\u3051\u307e\u308f\u3057\u76d7\u64ae\u30b9\u30da\u30b7\u30e3\u30eb 2\u6642\u9593\u3064\u3051\u307e\u308f\u3057\u7279\u6fc3\u7248120min", "issue_time": "2011-12-28", "company": "\u4fe1\u5dde\u66f8\u5e97$$$\u3064\u3061\u306e\u3053\u6620\u50cf", "duration": "121\u5206\u949f"}, {"id": "KSL-014", "page_url": "https://www.33fanhao.com/vod-read-id-147989.html", "title": "\u8fd1\u89aa\u30ec\u30ba \u6bcd\u3068\u5a18 \u30cd\u30aa\u30c9\u30e9\u30de 14", "issue_time": "2011-12-27", "company": "\u30a2\u30eb\u30d5\u30a1\u30fc\u30a4\u30f3\u30bf\u30fc\u30ca\u30b7\u30e7\u30ca\u30eb$$$\u89aa\u5b50\u4e3c", "duration": "48\u5206\u949f"}, {"id": "LHPT-011", "page_url": "https://www.33fanhao.com/vod-read-id-147988.html", "title": "\u4eba\u59bb\u9762\u8ac7\u30c9\u30ad\u30e5\u30e1\u30f3\u30c8 2 \u9ed2\u7530\u9ebb\u4e16", "issue_time": "2011-12-27", "company": "\u30e9\u30cf\u30a4\u30ca\u6771\u6d77$$$\u6708\u898b\u8349", "duration": "102\u5206\u949f"}, {"id": "LHBR-031", "page_url": "https://www.33fanhao.com/vod-read-id-147986.html", "title": "\u65e6\u90a3\u306e\u5c45\u306a\u3044\u9699\u306b\u884c\u308f\u308c\u308b \u9006\u3089\u3048\u306a\u3044\uff01\uff01 \u5ac1\u59d1\u30d1\u30ef\u30cf\u30e9\u30ec\u30ba\u76d7\u64ae 2", "issue_time": "2011-12-27", "company": "\u30e9\u30cf\u30a4\u30ca\u6771\u6d77$$$\u7d05\u4f10\u6298\u7f85", "duration": "116\u5206\u949f"}, {"id": "LHPT-010", "page_url": "https://www.33fanhao.com/vod-read-id-147987.html", "title": "\u79c1\u306e\u606f\u5b50\u3068\u4ea4\u63db\u3057\u306a\u3044\uff1f \u606f\u5b50\u4ea4\u63db\u7269\u8a9e 3", "issue_time": "2011-12-27", "company": "\u30e9\u30cf\u30a4\u30ca\u6771\u6d77$$$\u6708\u898b\u8349", "duration": "96\u5206\u949f"}, {"id": "LMHH-024", "page_url": "https://www.33fanhao.com/vod-read-id-147985.html", "title": "\u672c\u4eba\u306e\u898b\u3066\u306a\u3044\u9699\u306b\u3001\u89aa\u53cb\u306e\u5f7c\u5973\u306b\u75f4\u5973\u3089\u308c\u305f", "issue_time": "2011-12-27", "company": "\u30e9\u30cf\u30a4\u30ca\u6771\u6d77$$$\u30e9\u30de\u30cb\u30a2\uff3b\u6a2a\u6d5c\u95c7\u5009\u5eab\uff3d", "duration": "97\u5206\u949f"}, {"id": "LDJJ-511", "page_url": "https://www.33fanhao.com/vod-read-id-147984.html", "title": "\u30de\u25cb\u30b3\u30ae\u30ea\u30ae\u30ea\uff01\u30a2\u30ca\u30eb\u5168\u958b\u30c0\u30f3\u30b9", "issue_time": "2011-12-27", "company": "\u30de\u30cb\u30a2\u30bc\u30ed$$$JUICE\uff08\u30de\u30cb\u30a2\u30bc\u30ed\uff09", "duration": "239\u5206\u949f"}, {"id": "FBS-035", "page_url": "https://www.33fanhao.com/vod-read-id-147982.html", "title": "\u5de8\u4e73\u60a6\u697d35 \u91cc\u7f8e\u308b\u3046\u304b", "issue_time": "2011-12-27", "company": "\u30d7\u30fc\u30eb\u30af\u30e9\u30d6\u30fb\u30a8\u30f3\u30bf\u30c6\u30a4\u30f3\u30e1\u30f3\u30c8$$$Flower Works", "duration": "105\u5206\u949f"}, {"id": "FBS-034", "page_url": "https://www.33fanhao.com/vod-read-id-147983.html", "title": "\u5de8\u4e73\u60a6\u697d34 \u4e00\u30ce\u702c\u6075", "issue_time": "2011-12-27", "company": "\u30d7\u30fc\u30eb\u30af\u30e9\u30d6\u30fb\u30a8\u30f3\u30bf\u30c6\u30a4\u30f3\u30e1\u30f3\u30c8$$$Flower Works", "duration": "111\u5206\u949f"}, {"id": "LHJF-802", "page_url": "https://www.33fanhao.com/vod-read-id-147981.html", "title": "\u30a4\u30e4\u3089\u3057\u3044\u304a\u6bcd\u3055\u3093\u306e\u9854\u9a0e\u3001\u5c3b\u30b3\u30ad\u3067\u30a4\u30ab\u3055\u308c\u305f\u606f\u5b50\u305f\u3061", "issue_time": "2011-12-27", "company": "\u30de\u30cb\u30a2\u30bc\u30ed$$$F\u2019OXY", "duration": "139\u5206\u949f"}, {"id": "LQJI-803", "page_url": "https://www.33fanhao.com/vod-read-id-147980.html", "title": "\u304a\u9858\u3044\u3001\u30c8\u30a4\u30ec\u884c\u304b\u305b\u3066\u3063\uff01\u6392\u4fbf\u5973\u5b50\u6821\u751f 2", "issue_time": "2011-12-27", "company": "\u30de\u30cb\u30a2\u30bc\u30ed$$$INDY CORE", "duration": "142\u5206\u949f"}, {"id": "LHBB-099", "page_url": "https://www.33fanhao.com/vod-read-id-147979.html", "title": "\u52d5\u3051\u306a\u3044\u65e6\u90a3\u306e\u76ee\u306e\u524d\u3067\u4eba\u59bb\u3092\u5bdd\u53d6\u308b \u60aa\u8ceaSM\u8abf\u6559\u5e2b\u76d7\u64ae", "issue_time": "2011-12-27", "company": "\u30e9\u30cf\u30a4\u30ca\u6771\u6d77$$$\u9ed2\u4f10\u6298\u7f85", "duration": "111\u5206\u949f"}, {"id": "LMSS-010", "page_url": "https://www.33fanhao.com/vod-read-id-147978.html", "title": "\u53cb\u4eba\u3092\u91d1\u3067\u58f2\u308b\u5973\u5b50\u6821\u751f \u9ed2\u4eba\u30ec\u30a4\u30d7\u8acb\u8ca0\u4eba \u76d7\u64ae 2", "issue_time": "2011-12-27", "company": "\u30e9\u30cf\u30a4\u30ca\u6771\u6d77$$$\u30e9\u30de\u30cb\u30a2\uff3b\u6e0b\u8c37\u95c7\u5009\u5eab\uff3d", "duration": "75\u5206\u949f"}, {"id": "P-045", "page_url": "https://www.33fanhao.com/vod-read-id-147977.html", "title": "\u6b32\u5f35\u308a\u306a\u79d8\u6240 \u79cb\u53cb\u7d00\u4e4b", "issue_time": "2011-12-27", "company": "\u30ed\u30a4\u30e4\u30eb\u30a2\u30fc\u30c8$$$TOKYO\u30d1\u30ea\u30b9", "duration": "46\u5206\u949f"}, {"id": "ZCOL-006", "page_url": "https://www.33fanhao.com/vod-read-id-147993.html", "title": "Legend of \u5c3b\u4f1d\u8aac2 \u7f8e\u5de8\u5c3b\u4e94\u6642\u9593\u534a\u53ce\u9332", "issue_time": "2011-12-26", "company": "\u5b9f\u9332\u51fa\u7248$$$\u5b9f\u9332\u51fa\u7248", "duration": "334\u5206\u949f"}, {"id": "AXV-011", "page_url": "https://www.33fanhao.com/vod-read-id-147990.html", "title": "\u3046\u3057\u308d\u304b\u3089FUCK\u3059 \u897f\u6751\u7531\u7f8e", "issue_time": "2011-12-26", "company": "h.m.p$$$X", "duration": "51\u5206\u949f"}, {"id": "KSL-013", "page_url": "https://www.33fanhao.com/vod-read-id-147991.html", "title": "\u8fd1\u89aa\u30ec\u30ba \u6bcd\u3068\u5a18 \u30cd\u30aa\u30c9\u30e9\u30de 13", "issue_time": "2011-12-26", "company": "\u30a2\u30eb\u30d5\u30a1\u30fc\u30a4\u30f3\u30bf\u30fc\u30ca\u30b7\u30e7\u30ca\u30eb$$$\u89aa\u5b50\u4e3c", "duration": "48\u5206\u949f"}, {"id": "TAN-005", "page_url": "https://www.33fanhao.com/vod-read-id-147992.html", "title": "\u95a2\u897f\u6d41\u30cf\u30e1\u64ae\u308a \u30bf\u30f3\u30bb\u30ad\u306e\u30ef\u30ab\u30a4\u30e2\u30f3\u30cb\u30cf\u30de\u30b1\u30d8\u30f3\u30c7\u30a7 5 \u79cb\u6708\u674f\u5948", "issue_time": "2011-12-26", "company": "\u30ec\u30a4\u30c7\u30a3\u30c3\u30af\u30b9$$$TANSEKI", "duration": "90\u5206\u949f"}, {"id": "FAX-387", "page_url": "https://www.33fanhao.com/vod-read-id-147963.html", "title": "\u4e16\u306e\u70ba\u4eba\u306e\u70ba \u9055\u6cd5\u30d8\u30eb\u30d1\u30fc \u6027\u7684\u88cf\u4ecb\u8b77", "issue_time": "2011-12-25", "company": "FA\u30d7\u30ed$$$FA\u30d7\u30ed", "duration": "105\u5206\u949f"}, {"id": "SGSR-063", "page_url": "https://www.33fanhao.com/vod-read-id-147961.html", "title": "\u5f7c\u6c0f\u306e\u524d\u306b\u3082\u304b\u304b\u308f\u3089\u305a\u30a4\u30b8\u3089\u308c\u308b\u3068\u30cc\u30ec\u6fe1\u308c\uff01\uff1f \u62bc\u3057\u306b\u5f31\u3044\u8d85\u654f\u611f\u7d20\u4eba\u5a18\u305f\u3061 4\u6642\u9593", "issue_time": "2011-12-25", "company": "\u30d3\u30c3\u30b0\u30e2\u30fc\u30ab\u30eb$$$\u65b0\u6226\u7d44", "duration": "240\u5206\u949f"}, {"id": "JUMP-2277", "page_url": "https://www.33fanhao.com/vod-read-id-147962.html", "title": "\u8fd1\u89aa\u5b50\u25cf\u4ea4\u59e6\u30b9\u30ef\u30c3\u30d4\u30f3\u30b0 \u4e71\u4ea4\u30d0\u30b9\u30c4\u30a2\u30fc", "issue_time": "2011-12-25", "company": "JUMP$$$\u4e0b\u54c1\u5c4b\uff08JUMP\uff09", "duration": "175\u5206\u949f"}, {"id": "TMGI-027", "page_url": "https://www.33fanhao.com/vod-read-id-147958.html", "title": "\u8857\u89d2\u3067\u898b\u304b\u3051\u305f\u304a\u59c9\u3055\u3093\u306e\u98df\u3044\u8fbc\u307f\u30d1\u30f3\u30c1\u30e9", "issue_time": "2011-12-25", "company": "\u6771\u4eac\u30de\u30cbGUN\u2019S$$$\u30a2\u30a4\u30e9\u30f3\u30c9/\u6771\u4eac\u30de\u30cbGUN\u2019S", "duration": "83\u5206\u949f"}, {"id": "MASRS-030", "page_url": "https://www.33fanhao.com/vod-read-id-147959.html", "title": "\u5b9f\u9332 \u5f37\u59e6 \u5927\u5168\u96c6 \u56db\u6642\u9593 \u5f10", "issue_time": "2011-12-25", "company": "\u30d3\u30c3\u30b0\u30e2\u30fc\u30ab\u30eb$$$M\u30fbA\u30fbS\u30fbH", "duration": "240\u5206\u949f"}, {"id": "OKV-085", "page_url": "https://www.33fanhao.com/vod-read-id-147960.html", "title": "\u5b9f\u9332\u30fb\u66b4\u884c\u73fe\u5834\u30b3\u30ec\u30af\u30b7\u30e7\u30f3 2", "issue_time": "2011-12-25", "company": "\u7b20\u5009\u51fa\u7248\u793e$$$OKei", "duration": "90\u5206\u949f"}, {"id": "HYAZ-031", "page_url": "https://www.33fanhao.com/vod-read-id-147956.html", "title": "\u30c9\u30b9\u30b1\u30d9\u304a\u59c9\u3055\u3093\u306b\u30d1\u30f3\u30b9\u30c8\u3092\u30ce\u30fc\u30d1\u30f3\u3067\u7a7f\u304b\u305b\u3066\u73a9\u5177\u3067\u30a4\u30ab\u305b\u3066\u307f\u307e\u3057\u305f 2", "issue_time": "2011-12-25", "company": "\u30b8\u30e3\u30cd\u30b9$$$Fetish \u30d1\u30f3\u30b9\u30c8", "duration": "108\u5206\u949f"}, {"id": "DVBT-012", "page_url": "https://www.33fanhao.com/vod-read-id-147957.html", "title": "\u5b8c\u5168\u9632\u97f3\u500b\u5ba4 \u30d3\u30c7\u30aa\u30dc\u30c3\u30af\u30b9\u306e\u51c4\u3044\u30aa\u30ca\u30cb\u30fc\u76d7\u64ae 12", "issue_time": "2011-12-25", "company": "\u30f4\u30a1\u30eb\u30c7\u30a3\u30fc\uff08\u76d7\u64ae\uff09/\u5984\u60f3\u65cf$$$\u30f4\u30a1\u30eb\u30c7\u30a3\u30fc\uff08\u76d7\u64ae\uff09/\u5984\u60f3\u65cf", "duration": "233\u5206\u949f"}, {"id": "JUMP-2280", "page_url": "https://www.33fanhao.com/vod-read-id-147953.html", "title": "\u3053\u25cf\u3082\u30aa\u30ca\u30cb\u30fc16\u6642\u9593111\u4eba \u7f8e\u25cf\u5973\u53b3\u9078", "issue_time": "2011-12-25", "company": "JUMP$$$\u4e0b\u54c1\u5c4b\uff08JUMP\uff09", "duration": "961\u5206\u949f"}, {"id": "AXAQ-006", "page_url": "https://www.33fanhao.com/vod-read-id-147954.html", "title": "\u606f\u5b50\u304c\u75f4\u7fa9\u6bcd\u3092\u8abf\u6559\u3059\u308b\u8fd1\u89aa\u76f8\u59e6 DX 4\u6642\u9593", "issue_time": "2011-12-25", "company": "\u30b8\u30e3\u30cd\u30b9$$$\u8276\u5973", "duration": "243\u5206\u949f"}, {"id": "NACR-018", "page_url": "https://www.33fanhao.com/vod-read-id-147955.html", "title": "\u7279\u9078\uff01\u5de8\u4e73\u5965\u69d8 4\u6642\u9593 \u5176\u306e\u4e8c", "issue_time": "2011-12-25", "company": "\u30d7\u30e9\u30cd\u30c3\u30c8\u30d7\u30e9\u30b9$$$\u4e03\u72d7\u7559", "duration": "238\u5206\u949f"}, {"id": "CURO-003", "page_url": "https://www.33fanhao.com/vod-read-id-147951.html", "title": "\u5f7c\u6c0f\u306b\u3088\u3063\u3066\u76d7\u64ae\u3055\u308c\u305f\u30ea\u30a2\u30eb\u5f7c\u5973\u3068\u306e\u65e5\u5e38\u30bb\u30c3\u30af\u30b9", "issue_time": "2011-12-25", "company": "\u9ed2\u7f8a/\u5984\u60f3\u65cf$$$\u9ed2\u7f8a/\u5984\u60f3\u65cf", "duration": "239\u5206\u949f"}, {"id": "CSZ-029", "page_url": "https://www.33fanhao.com/vod-read-id-147952.html", "title": "\u300c\u8d64\u5916\u7dda\u76d7\u64ae\u30b7\u30ea\u30fc\u30ba\u300dVol.29 CAR SEX", "issue_time": "2011-12-25", "company": "\u7121\u5370\u30e0\u30fc\u30d3\u30fc$$$\u7121\u5370\u30e0\u30fc\u30d3\u30fc", "duration": "152\u5206\u949f"}, {"id": "RCSP-005", "page_url": "https://www.33fanhao.com/vod-read-id-147947.html", "title": "\u30a2\u30b9\u30ea\u30fc\u30c8\u5c11\u5973 \u559c\u591a\u5d8b\u3042\u305a\u3055", "issue_time": "2011-12-25", "company": "\u8c4a\u5f66$$$\u8c4a\u5f66", "duration": "110\u5206\u949f"}, {"id": "FECH-011", "page_url": "https://www.33fanhao.com/vod-read-id-147948.html", "title": "\u3080\u3063\u3061\u3080\u3063\u3061\u30bf\u30a4\u30c8\u306a\u30b9\u30fc\u30c4\u30b9\u30c8\u30c3\u30ad\u30f3\u30b0\u6311\u767a\u3059\u308b\u7f8e\u4ebaOL\u305f\u3061\u306e\u304a\u5c3b\u30b3\u30ad2 48\u4eba", "issue_time": "2011-12-25", "company": "\u30ec\u30c3\u30c9$$$FECH", "duration": "232\u5206\u949f"}, {"id": "HFCM-013", "page_url": "https://www.33fanhao.com/vod-read-id-147949.html", "title": "heavy fetish \u5b9f\u306f\u7537\u3063\u307d\u3044\u5973\u306e\u5b50\u306b\u72af\u3055\u308c\u3066\u307f\u305f", "issue_time": "2011-12-25", "company": "\u30b1\u30e9\u5de5\u623f$$$\u30b1\u30e9\u5de5\u623f", "duration": "94\u5206\u949f"}, {"id": "CURO-002", "page_url": "https://www.33fanhao.com/vod-read-id-147950.html", "title": "\u771f\u3063\u663c\u9593\u304b\u3089\u30d0\u30b9\u30eb\u30fc\u30e0\u3067\u733f\u306e\u3088\u3046\u306b\u4ea4\u5c3e\u3059\u308b\u4e0d\u502b\u59bb\u305f\u3061", "issue_time": "2011-12-25", "company": "\u9ed2\u7f8a/\u5984\u60f3\u65cf$$$\u9ed2\u7f8a/\u5984\u60f3\u65cf", "duration": "79\u5206\u949f"}, {"id": "TMGI-034", "page_url": "https://www.33fanhao.com/vod-read-id-147945.html", "title": "\u304a\u5ea7\u6577\u30bb\u30af\u30ad\u30e3\u30d0\u5b22\u5e97\u5185\u30aa\u30ca\u30cb\u30fc\u96a0\u3057\u64ae\u308a\uff01\uff01", "issue_time": "2011-12-25", "company": "\u6771\u4eac\u30de\u30cbGUN\u2019S$$$\u30a2\u30a4\u30e9\u30f3\u30c9/\u6771\u4eac\u30de\u30cbGUN\u2019S", "duration": "83\u5206\u949f"}, {"id": "TMGI-032", "page_url": "https://www.33fanhao.com/vod-read-id-147946.html", "title": "\u73fe\u5f79\u5973\u5b50\u6821\u751f\u5728\u7c4d\u30d4\u30f3\u30b5\u30ed\u6f5c\u5165\u76d7\u64ae", "issue_time": "2011-12-25", "company": "\u6771\u4eac\u30de\u30cbGUN\u2019S$$$\u30a2\u30a4\u30e9\u30f3\u30c9/\u6771\u4eac\u30de\u30cbGUN\u2019S", "duration": "121\u5206\u949f"}, {"id": "ZOS-001", "page_url": "https://www.33fanhao.com/vod-read-id-147942.html", "title": "\u5973\u738b\u69d8\u306f\u98a8\u9593\u3086\u307f", "issue_time": "2011-12-25", "company": "AVS collector\u2019s$$$Black Maria", "duration": "87\u5206\u949f"}, {"id": "ARKJ-004", "page_url": "https://www.33fanhao.com/vod-read-id-147943.html", "title": "R30 Glamorous 3", "issue_time": "2011-12-25", "company": "\u30c7\u30b8\u30bf\u30eb\u30a2\u30fc\u30af$$$digital ark\uff08\u30c7\u30b8\u30bf\u30eb\u30a2\u30fc\u30af\uff09", "duration": "125\u5206\u949f"}]