{"result": {"next": 38, "last": 84, "lastPage": false, "totalPage": 84, "prev": 36, "count": 833, "firstResult": 360, "funcParam": "", "orderBy": "", "pageSize": 10, "list": [{"purchaseItemName": "服务类・信息技术服务・软件开发服务", "projId": "2d891b89676a40f7897070506ae310ae", "pLmId": "", "publishDate": "2021-06-16 16:23:12", "projNumber": "ZJZC-(2021)公字第0013号", "title": "【中标公告】镇江市生态环境大数据归集和共享服务项目招标中标结果公告", "type": 1, "content": "", "lmId": "", "purchaseWay": "cgfs001", "id": "7931cf438f75491387b1b30551a8c956", "pZoneCode": "320000", "zoneName": "镇江市", "lmName": "", "summary": "中 标 结 果 公 告一、项目编号：ZJZC-(2021)公字第0013号 一、项目名称：镇江市生态环境大数据归集和共享服务项目招标 三、中标（成交）信息供应商名称：神彩科技股份有限公司   供应商地址：苏州市苏州工业园区娄阳路12号  中标金额：2988000.00元   四", "ggCode": "zbgg", "projName": "镇江市生态环境大数据归集和共享服务项目招标", "agentName": "镇江市生态环境局", "buyerName": "镇江市生态环境局", "pZoneName": "江苏省", "ppp": "0", "pLmName": "", "publish": true, "files": [{"name": "ZJZC-(2021)公字第0013号 镇江市生态环境大数据归集和共享服务项目招标文件.pdf", "url": "http://www.ccgp-jiangsu.gov.cn//webfile/jiangsu/202106/1623828267013062508.pdf"}], "siteId": "1", "purchaseItem": "C0101", "zoneCode": "321100"}, {"projId": "89cbe1ecfcd049f6816005301b81fafc", "pLmId": "", "publishDate": "2021-06-16 16:23:05", "projNumber": "JSJC20210414", "title": "南京市公安局雨花台分局雨花台派出所室内装修工程成交公告", "type": 1, "content": "", "lmId": "", "purchaseWay": "cgfs008", "id": "a0d36a050f794430a5fb2038ba9159ab", "pZoneCode": "320100", "zoneName": "雨花台区", "lmName": "", "summary": "江苏建诚工程咨询有限公司受南京市公安局雨花台分局委托，就“南京市公安局雨花台分局雨花台派出所室内装修工程”进行竞争性磋商采购，现将成交结果公布如下:一、项目编号:JSJC20210414  二、项目名称: 南京市公安局雨花台分局雨花台派出所室内装修工程三、成交信息供应商名称：南京茗赛源建设有限公司供应商地址：", "ggCode": "cjgg", "projName": "南京市公安局雨花台分局雨花台派出所室内装修工程", "agentName": "江苏建诚工程咨询有限公司", "buyerName": "南京市公安局雨花台分局", "pZoneName": "南京市", "ppp": "0", "pLmName": "", "publish": true, "files": [{"name": "（竞争性磋商文件） 南京市公安局雨花台区派出所装修发出版.doc", "url": "http://njgc.jfh.com//provider/20210616/1623823969189.doc"}], "siteId": "1", "purchaseItem": "B07", "zoneCode": "320114"}, {"projId": "b6bda1dbfd9f472897f62afe9812c3e4", "pLmId": "", "publishDate": "2021-06-16 16:22:58", "projNumber": "JNZC-2019GK0109", "title": "【JNZC-2021GK0040】江宁区芳园西路小学等校班级多媒体设备采购结果公告", "type": 1, "content": "", "lmId": "", "purchaseWay": "cgfs001", "id": "18fd6515924744738d1e1b62c1c89e12", "pZoneCode": "320100", "zoneName": "江宁区", "lmName": "", "summary": "一、项目编号：JNZC-2021GK0040二、项目名称：江宁区芳园西路小学等校班级多媒体设备三、中标（成交）信息 分包号 无中标供应商名称：淮安市鑫鑫教育用品有限公司中标供应商地址：淮安市淮安区施河镇太平路83号中标金额：￥2,642,560.00元（单位：人民币）四、主要标的信息：产品1产品名称: 交互式", "ggCode": "zbgg", "projName": "江宁区芳园西路小学弱电智能化设备网上公开招标公告", "agentName": "南京市公共资源交易中心江宁分中心", "buyerName": "南京市江宁区教育技术装备中心", "pZoneName": "南京市", "ppp": "0", "pLmName": "", "publish": true, "files": [{"name": "JNZC-2021GK0040 江宁区芳园西路小学等校班级多媒体设备 0521 发布.pdf", "url": "http://www.ccgp-jiangsu.gov.cn//webfile/jiangsu/202106/1623828522389003479.pdf"}], "siteId": "1", "purchaseItem": "A020899", "zoneCode": "320115"}, {"projId": "3f429735ff674258b42f0545abb7e731", "pLmId": "", "publishDate": "2021-06-16 16:22:51", "projNumber": "QC-2021052509E", "title": "南京市龙江体育运动学校关于幕墙安全性能检测与鉴定服务项目的成交结果公告", "type": 1, "content": "", "lmId": "", "purchaseWay": "cgfs003", "id": "0514b54b38d94e20b98064b5601a1060", "pZoneCode": "320100", "zoneName": "鼓楼区", "lmName": "", "summary": "一、项目编号：QC-2021052509E二、项目名称：幕墙安全性能检测与鉴定服务项目三、成交信息供应商名称：江苏华科建设工程质量检测有限公司供应商地址：南京市江北新区万寿路15号南京工大科技产业园东区成交总价金额：人民币肆万柒仟捌佰元整（￥47,800.00）。四、主要标的信息（服务类）服务名称：幕墙安全性能检测与鉴", "ggCode": "cjgg", "projName": "幕墙安全性能检测与鉴定服务项目", "agentName": "江苏柒采招标代理有限公司", "buyerName": "南京市龙江体育运动学校", "pZoneName": "南京市", "ppp": "0", "pLmName": "", "publish": true, "files": [{"name": "中小企业声明函.pdf", "url": "http://njgc.jfh.com//provider/20210616/1623829950619.pdf"}, {"name": "09E（06.08定）幕墙安全性检测.pdf", "url": "http://njgc.jfh.com//provider/20210616/1623829942057.pdf"}], "siteId": "1", "purchaseItem": "B0511", "zoneCode": "320106"}, {"purchaseItemName": "其他医疗设备", "projId": "0a4814c358a54eb3a02330314a2a37ef", "pLmId": "", "publishDate": "2021-06-16 16:22:45", "projNumber": "WXWJCG2021-029[20210514101452]", "title": "无锡市卫生健康采购与药具管理中心关于江南大学附属医院全自动片剂摆药机项目的中标公告", "type": 1, "content": "", "lmId": "", "purchaseWay": "cgfs001", "id": "786cc259cb2047cdbe8f2f804c2bed0c", "pZoneCode": "320000", "zoneName": "无锡市", "lmName": "", "summary": "一、项目编号：WXWJCG2021-029二、项目名称：江南大学附属医院全自动片剂摆药机项目三、中标（成交）信息供应商名称：无锡市海尔斯科技有限公司（统一社会信用代码：913202146770049279）供应商地址： 无锡市梁溪区五里新村98-1-6-07中标（成交）金额：1230000元四、主要标的信息货物类名称：", "ggCode": "zbgg", "projName": "江南大学附属医院全自动片剂摆药机项目", "agentName": "无锡市卫生健康采购与药具管理中心", "buyerName": "江南大学附属医院", "pZoneName": "江苏省", "ppp": "0", "pLmName": "", "publish": true, "files": [{"name": "采购文件WXWJCG2021-029.docx", "url": "http://wx-gov-open-doc.oos-website-cn.oos-cn.ctyunapi.cn/1023FP/6a209729-689f-4205-84d0-823cdc4b2682.docx"}], "siteId": "1", "purchaseItem": "A032099", "zoneCode": "320200"}, {"projId": "332e933389474eca89101797bf22d1dd", "pLmId": "", "publishDate": "2021-06-16 16:22:36", "projNumber": "QC-2021051931C", "title": "2021网络安全专项行动服务项目  成交公告", "type": 1, "content": "", "lmId": "", "purchaseWay": "cgfs008", "id": "e8c10ce587084c0a80f051df6bd7b523", "pZoneCode": "", "zoneName": "江苏省", "lmName": "", "summary": "一、项目编号：QC-2021051931C二、项目名称：2021网络安全专项行动服务项目三、成交信息（一）成交供应商名称：江苏金盾检测技术股份有限公司成交供应商地址：南京市玄武区徐庄软件园二期聚慧园5号楼12层成交金额：人民币贰拾万元整（￥200,000.00元）（二）成交供应商名称：江苏天创科技有限公司成交供应商地址", "ggCode": "cjgg", "projName": "2021网络安全专项行动服务项目", "agentName": "江苏柒采招标代理有限公司", "buyerName": "江苏省卫生统计信息中心", "pZoneName": "", "ppp": "0", "pLmName": "", "publish": true, "files": [{"name": "（31C）20221网络安全专项行动服务项目 磋商文件（5.31定稿）.pdf", "url": "http://www.ccgp-jiangsu.gov.cn//webfile/jiangsu/202106/1623831735752046870.pdf"}], "siteId": "1", "purchaseItem": "C99", "zoneCode": "320000"}, {"projId": "00e21fe2933843ccac7ae410f80c4c56", "pLmId": "", "publishDate": "2021-06-16 16:22:25", "projNumber": "JSJX20210526GF", "title": "江苏省地质环境勘查院南京安德门基地改造重建工程项目A座屋顶光伏发电系统采购及安装中标公告", "type": 1, "content": "", "lmId": "", "purchaseWay": "cgfs001", "id": "c3d769dd54d048ebb56a98583dad53c4", "pZoneCode": "320100", "zoneName": "雨花台区", "lmName": "", "summary": "一、项目编号：JSJX20210526GF二、项目名称：江苏省地质环境勘查院南京安德门基地改造重建工程项目A座屋顶光伏发电系统采购及安装三、中标信息供应商名称：江苏科大环保装备制造有限公司供应商地址：江苏省南京市江北新区浦外路28号中标金额：人民币贰拾贰万叁仟陆佰元整（￥223600元）四、主要标的信息名称", "ggCode": "zbgg", "projName": "江苏省地质环境勘查院南京安德门基地改造重建工程项目A座屋顶光伏发电系统采购及安装", "agentName": "江苏省建信招投标有限公司", "buyerName": "江苏省地质环境勘查院", "pZoneName": "南京市", "ppp": "0", "pLmName": "", "publish": true, "files": [{"name": "光伏发电系统采购及安装招标文件20210526-发.doc", "url": "http://www.ccgp-jiangsu.gov.cn//webfile/jiangsu/202106/1623829222808031057.doc"}], "siteId": "1", "purchaseItem": "A10", "zoneCode": "320114"}, {"purchaseItemName": "其他服务", "projId": "2baf0e7adf38401bb06a19c6e51d04b7", "pLmId": "", "publishDate": "2021-06-16 16:22:18", "projNumber": "SZYJ2021-WJ-C-018", "title": "苏州市吴江区社会保险基金管理中心关于2021年工伤预防培训改善项目的中标公示", "type": 1, "content": "", "lmId": "", "purchaseWay": "cgfs008", "id": "1dbb5a712eae47b18660e5bbe99aaa64", "pZoneCode": "320000", "zoneName": "苏州市", "lmName": "", "summary": "一、项目编号：SZYJ2021-WJ-C-018二、项目名称：2021年工伤预防培训改善项目三、中标（成交）信息供应商名称：苏州工业园区人力资源开发有限公司供应商地址：苏州工业园区旺墩路168号市场大厦中标（成交）金额：人民币陆拾捌万捌仟捌佰元整（小写￥：688800.00）四、主要标的信息服务类项目名称：2021年工", "ggCode": "cjgg", "projName": "2021年工伤预防培训改善项目", "agentName": "苏州市宇杰工程技术服务咨询有限公司", "buyerName": "苏州市吴江区社会保险基金管理中心", "pZoneName": "江苏省", "ppp": "0", "pLmName": "", "publish": true, "files": [{"name": "1623828017901d8931866d20d4908b1f6dfad1befdb552021年工伤预防培训改善5", "url": "http://czju.suzhou.gov.cn/zfcg/informations/rules/downFile.action?filePath=fab7458cf9d94696a8ffa85704e839c6"}], "siteId": "1", "purchaseItem": "C99", "zoneCode": "320500"}, {"projId": "88fbc68588684a3cbe92e74d4441ebd1", "pLmId": "", "publishDate": "2021-06-16 16:22:08", "projNumber": "SNZX-20210413", "title": "非财政补助资金1200万元以竞争性方式选择银行定期存放中标结果公告", "type": 1, "content": "", "lmId": "", "purchaseWay": "cgfs001", "id": "0af35dae009b4872bad137d3119d231d", "pZoneCode": "", "zoneName": "江苏省", "lmName": "", "summary": "南京苏宁工程咨询有限公司受《江苏安全生产》编辑部委托，就非财政补助资金1200万元以竞争性方式选择银行定期存放进行公开招标，按规定程序进行了开标、评标、定标，现就本次招标的中标结果公布如下：一、项目编号：SNZX-20210413二、项目名称：非财政补助资金1200万元以竞争性方式选择银行定期存放三、中标信息供应商名称", "ggCode": "zbgg", "projName": "非财政补助资金1200万元以竞争性方式选择银行定期存放", "agentName": "南京苏宁工程咨询有限公司", "buyerName": "《江苏安全生产》编辑部", "pZoneName": "", "ppp": "0", "pLmName": "", "publish": true, "files": [{"name": "（招标文件）非财政补助资金1200万元以竞争性方式选择银行定期存放.pdf", "url": "http://www.ccgp-jiangsu.gov.cn//webfile/jiangsu/202106/1623811116603086632.pdf"}], "siteId": "1", "purchaseItem": "C", "zoneCode": "320000"}, {"purchaseItemName": "构筑物施工", "projId": "a56c70e923944e739f1d6dfca7cc68b8", "pLmId": "", "publishDate": "2021-06-16 16:22:01", "projNumber": "HXZX2021-SX-C-005-001", "title": "苏州市相城区人民政府漕湖街道办事处关于漕湖花园一社区停车位改造工程项目的成交公告", "type": 1, "content": "", "lmId": "", "purchaseWay": "cgfs008", "id": "c1b44895419541568cc91fc9958963b1", "pZoneCode": "320000", "zoneName": "苏州市", "lmName": "", "summary": "一、项目编号：HXZX2021-SX-C-005-001二、项目名称：漕湖花园一社区停车位改造工程三、成交信息供应商名称：江苏鑫升建市政工程有限公司供应商地址：苏州吴中区东方大道988号江苏吴中大厦1008室 成交金额：人民币壹佰壹拾肆万捌仟元整（￥：1148000.00元）四、主要标的信息工程类名称：漕湖花园一社区停", "ggCode": "cjgg", "projName": "漕湖花园一社区停车位改造工程", "agentName": "苏州鸿鑫工程咨询有限公司", "buyerName": "漕湖街道办事处", "pZoneName": "江苏省", "ppp": "0", "pLmName": "", "publish": true, "files": [{"name": "16238281575340455a17cf78d4004a3a4131392611c60HXZX2021-SX-C-005-001的相关附件.zip", "url": "http://czju.suzhou.gov.cn/zfcg/informations/rules/downFile.action?filePath=8c3e1c523f0e417ebea02137c1b45ef8"}], "siteId": "1", "purchaseItem": "B02", "zoneCode": "320500"}], "funcName": "page", "firstPage": false, "maxResults": 10, "pageNo": 37, "notCount": false, "disabled": false, "first": 1}, "code": 200}